{"packages":{"classic":{"css":true,"extTier":"pro","included":true,"language":{"js":{"input":{"version":"ES5"}}},"namespace":"Ext","required":true,"requires":["ext","core"],"version":"7.0.0"},"cmd":{"version":"7.0.0.40"},"core":{"css":true,"extTier":"pro","included":true,"required":true,"requires":["ext","classic"],"version":"7.0.0"},"ext":{"css":true,"extTier":"pro","included":true,"language":{"js":{"input":{"version":"ES5"}}},"license":"gpl","namespace":"Ext","required":true,"requires":[],"version":"7.0.0"},"font-awesome":{"css":true,"extTier":"pro","included":true,"namespace":"Ext","required":true,"requires":["ext","core","classic","theme-base","theme-neutral","theme-neptune"],"theme":"theme-neptune","version":"7.0.0"},"font-ext":{"css":true,"extTier":"pro","included":true,"namespace":"Ext","required":true,"requires":["ext","core","classic","theme-base","theme-neutral","theme-neptune"],"theme":"theme-neptune","version":"7.0.0"},"theme-base":{"css":true,"extTier":"pro","included":true,"namespace":"Ext","required":true,"requires":["ext","core","classic"],"version":"7.0.0"},"theme-neptune":{"css":true,"extTier":"pro","extend":"theme-neutral","included":true,"namespace":"Ext","required":true,"requires":["ext","core","classic","theme-base","theme-neutral"],"version":"7.0.0"},"theme-neutral":{"css":true,"extTier":"pro","extend":"theme-base","included":true,"namespace":"Ext","required":true,"requires":["ext","core","classic","theme-base"],"version":"7.0.0"},"theme-triton":{"css":true,"extTier":"pro","extend":"theme-neptune","included":true,"namespace":"Ext","required":true,"requires":["ext","core","classic","theme-base","theme-neutral","theme-neptune","font-awesome","font-ext"],"version":"7.0.0"},"ux":{"css":true,"extTier":"pro","included":true,"namespace":"Ext","required":true,"requires":["ext","core","classic"],"version":"7.0.0"}},"js":[{"path":"cms/ui/generatedFiles/app.js"}],"css":[{"remote":false,"exclude":["fashion"],"path":"cms/ui/resources/Cetera-all_1.css"},{"remote":false,"exclude":["fashion"],"path":"cms/ui/resources/Cetera-all_2.css"}],"cache":{"enable":true,"deltas":false},"fashion":{"inliner":{"enable":false},"missingParameters":"error"},"name":"Cetera","namespace":"Cetera","version":"1.0.0.0","framework":"ext","template":"classicdesktop","loader":{"cache":"20210316184807","cacheParam":"_dc"},"id":"fe7642bb-abb4-476e-9cf3-00467c3fe18b","toolkit":"classic","theme":"theme-triton","hash":"d084c98cd010c520e3c51f1b26be5891cb6488b3","profile":"desktop","resources":{"path":"cms/ui/resources","shared":"cms/ui/resources"}}